hitomi/__init__.py
hitomi/main.py
hitomi/version.py
hitomi/commands/__init__.py
hitomi/commands/abi.py
hitomi/commands/accounts.py
hitomi/commands/checksum.py
hitomi/commands/contract.py
hitomi/commands/erc20/__init__.py
hitomi/commands/erc20/abi.json
hitomi/commands/uniswap/__init__.py
hitomi/commands/uniswap/pair_abi.json
hitomi/console/__init__.py
hitomi/console/__main__.py
hitomi/network/__init__.py
hitomi/network/web3.py
hitomi-0.3.5.dist-info/METADATA
hitomi-0.3.5.dist-info/WHEEL
hitomi-0.3.5.dist-info/entry_points.txt
hitomi-0.3.5.dist-info/top_level.txt
hitomi-0.3.5.dist-info/RECORD
