Metadata-Version: 2.1
Name: hitomi
Version: 0.3.5
Summary: UNKNOWN
Home-page: https://github.com/cleanunicorn/hitomi
Author: Daniel Luca
Author-email: daniel.luca@consensys.net
License: MIT
Platform: UNKNOWN
Requires-Dist: web3 (==5.7.0)
